jupyterlab_nord_theme/__init__.py
jupyterlab_nord_theme/labextension/build_log.json
jupyterlab_nord_theme/labextension/package.json
jupyterlab_nord_theme/labextension/static/lib_index_js.08e6209e1dc2d44ce80d.js
jupyterlab_nord_theme/labextension/static/lib_index_js.08e6209e1dc2d44ce80d.js.map
jupyterlab_nord_theme/labextension/static/remoteEntry.ba6d31296313be264988.js
jupyterlab_nord_theme/labextension/static/remoteEntry.ba6d31296313be264988.js.map
jupyterlab_nord_theme/labextension/static/style.js
jupyterlab_nord_theme/labextension/static/style_index_js.dfe662080fbf3c452adf.js
jupyterlab_nord_theme/labextension/static/style_index_js.dfe662080fbf3c452adf.js.map
jupyterlab_nord_theme/labextension/themes/jupyterlab-nord-theme/index.css
jupyterlab_nord_theme/labextension/themes/jupyterlab-nord-theme/index.js
jupyterlab_nord_theme-0.1.1.data/data/share/jupyter/labextensions/jupyterlab-nord-theme/build_log.json
jupyterlab_nord_theme-0.1.1.data/data/share/jupyter/labextensions/jupyterlab-nord-theme/package.json
jupyterlab_nord_theme-0.1.1.data/data/share/jupyter/labextensions/jupyterlab-nord-theme/static/lib_index_js.08e6209e1dc2d44ce80d.js
jupyterlab_nord_theme-0.1.1.data/data/share/jupyter/labextensions/jupyterlab-nord-theme/static/lib_index_js.08e6209e1dc2d44ce80d.js.map
jupyterlab_nord_theme-0.1.1.data/data/share/jupyter/labextensions/jupyterlab-nord-theme/static/remoteEntry.ba6d31296313be264988.js
jupyterlab_nord_theme-0.1.1.data/data/share/jupyter/labextensions/jupyterlab-nord-theme/static/remoteEntry.ba6d31296313be264988.js.map
jupyterlab_nord_theme-0.1.1.data/data/share/jupyter/labextensions/jupyterlab-nord-theme/static/style.js
jupyterlab_nord_theme-0.1.1.data/data/share/jupyter/labextensions/jupyterlab-nord-theme/static/style_index_js.dfe662080fbf3c452adf.js
jupyterlab_nord_theme-0.1.1.data/data/share/jupyter/labextensions/jupyterlab-nord-theme/static/style_index_js.dfe662080fbf3c452adf.js.map
jupyterlab_nord_theme-0.1.1.dist-info/METADATA
jupyterlab_nord_theme-0.1.1.dist-info/WHEEL
jupyterlab_nord_theme-0.1.1.dist-info/licenses/LICENSE
jupyterlab_nord_theme-0.1.1.dist-info/RECORD
