Metadata-Version: 2.4
Name: jupyterlab-nord-theme
Version: 0.1.1
Summary: An arctic, north-bluish clean and elegant JupyterLab theme based on the Nord color palette
Project-URL: Homepage, https://github.com/carlyou/jupyterlab-nord-theme
Project-URL: Bug-Tracker, https://github.com/carlyou/jupyterlab-nord-theme/issues
Project-URL: Repository, https://github.com/carlyou/jupyterlab-nord-theme.git
Author-email: carlyou <carlyou@users.noreply.github.com>
License: MIT License
License-File: LICENSE
Keywords: Jupyter,JupyterLab,JupyterLab4,Nord,theme
Classifier: Framework :: Jupyter
Classifier: Framework :: Jupyter :: JupyterLab
Classifier: Framework :: Jupyter :: JupyterLab :: 4
Classifier: Framework :: Jupyter :: JupyterLab :: Extensions
Classifier: Framework :: Jupyter :: JupyterLab :: Extensions :: Prebuilt
Classifier: License :: OSI Approved :: MIT License
Classifier: Programming Language :: Python
Classifier: Programming Language :: Python :: 3
Classifier: Programming Language :: Python :: 3.8
Classifier: Programming Language :: Python :: 3.9
Classifier: Programming Language :: Python :: 3.10
Classifier: Programming Language :: Python :: 3.11
Classifier: Programming Language :: Python :: 3.12
Requires-Python: >=3.9
Requires-Dist: jupyterlab<5,>=4.0.0
